django_jsonschema/__init__.py
django_jsonschema/forms.py
django_jsonschema/models.py
django_jsonschema/validators.py
django_jsonschema/postgres/__init__.py
django_jsonschema/postgres/models.py
django_jsonschema2-0.2.1.dist-info/DESCRIPTION.rst
django_jsonschema2-0.2.1.dist-info/METADATA
django_jsonschema2-0.2.1.dist-info/RECORD
django_jsonschema2-0.2.1.dist-info/WHEEL
django_jsonschema2-0.2.1.dist-info/metadata.json
django_jsonschema2-0.2.1.dist-info/top_level.txt
