Metadata-Version: 2.0
Name: django-jsonschema2
Version: 0.2.1
Summary: Django JSONSchema
Home-page: https://github.com/hypc/django-jsonschema
Author: hypc
Author-email: h_yp00@163.com
License: MIT
Platform: UNKNOWN
Classifier: Environment :: Web Environment
Classifier: Framework :: Django
Classifier: License :: OSI Approved :: MIT License
Classifier: Programming Language :: Python :: 3
Classifier: Programming Language :: Python :: 3.2
Classifier: Programming Language :: Python :: 3.3
Classifier: Programming Language :: Python :: 3.4
Classifier: Programming Language :: Python :: 3.5
Classifier: Intended Audience :: Developers
Classifier: Topic :: Internet
Requires-Dist: jsonschema
Requires-Dist: django
